cellunet/Dockerfile
cellunet/LICENSE
cellunet/README.md
cellunet/__init__.py
cellunet/data/composite_nuc.tif
cellunet/data/labels0.tif
cellunet/data/labels1.tif
cellunet/data/nuc0.png
cellunet/data/nuc1.png
cellunet/etc/startup.sh
cellunet/on_the_fly.py
cellunet/patches.py
cellunet/predict.py
cellunet/tests_augment.py
cellunet/tfutils.py
cellunet/train.py
cellunet/utils/__init__.py
cellunet/utils/_allen.py
cellunet/utils/augmentation.py
cellunet/utils/metrics.py
cellunet/utils/model_builder.py
cellunet/utils/objectives.py
cellunet-0.2.2.dist-info/WHEEL
cellunet-0.2.2.dist-info/METADATA
cellunet-0.2.2.dist-info/RECORD
