Metadata-Version: 2.1
Name: cellunet
Version: 0.2.2
Summary: 
Home-page: UNKNOWN
License: UNKNOWN
Author: Takamasa Kudo
Author-email: kudo@stanford.edu
Requires-Python: >=3.5,<4.0
Classifier: Programming Language :: Python :: 3
Classifier: Programming Language :: Python :: 3.5
Classifier: Programming Language :: Python :: 3.6
Classifier: Programming Language :: Python :: 3.7
Requires-Dist: keras (==2.0.0)
Requires-Dist: numpy (==1.14.6)
Requires-Dist: pandas (==0.23.0)
Requires-Dist: scikit-image (==0.14.1)
Requires-Dist: scipy (==1.1.0)
Requires-Dist: tensorflow (==1.8.0)
Requires-Dist: tifffile (>=2019.1,<2020.0)
